Metadata-Version: 2.4
Name: llama-index-retrievers-duckdb-retriever
Version: 0.5.1
Summary: llama-index retrievers duckdb-retriever integration
Author-email: Your Name <you@example.com>
License-Expression: MIT
License-File: LICENSE
Requires-Python: <4.0,>=3.9
Requires-Dist: duckdb<2,>=1.1.3
Requires-Dist: llama-index-core<0.15,>=0.13.0
